{"cameraMode":{"drawMode":0,"name":"Shaded","section":"Shading Mode"},"sceneLighting":false,"audioPlay":false,"sceneViewState":{"m_AlwaysRefresh":false,"showFog":true,"showSkybox":false,"showFlares":true,"showImageEffects":true,"showParticleSystems":true,"showVisualEffectGraphs":true,"m_FxEnabled":true},"in2DMode":false,"pivot":{"x":0.02232271432876587,"y":0.375,"z":0.2682323455810547},"rotation":{"x":0.21858543157577516,"y":0.06142544001340866,"z":-0.013788115233182907,"w":0.9737860560417175},"size":1.6688268184661866,"orthographic":false}